MANIFEST.in
README
setup.py
lib2d/__init__.py
lib2d/finalizer.py
lib2d.egg-info/PKG-INFO
lib2d.egg-info/SOURCES.txt
lib2d.egg-info/dependency_links.txt
lib2d.egg-info/top_level.txt
src/alloc.h
src/atlas.c
src/atlas.h
src/atlas_bank.c
src/atlas_bank.h
src/drawable.c
src/drawable.h
src/error.c
src/error.h
src/gl_core_3_3.c
src/gl_core_3_3.h
src/lib2d.c
src/lib2dthread.h
src/python.c
src/render.c
src/render.h
src/render_api.h
src/render_gl.c
src/small_vec.h
src/stb_image.c
src/stb_image.h
src/stb_truetype.c
src/stb_truetype.h
src/stretchy_buffer.h
src/text.c