Metadata-Version: 1.1
Name: lib2d
Version: 0.0.8
Summary: A fast and simple 2D sprite rendering library for games
Home-page: http://lib2d.com
Author: Joseph Marshall
Author-email: jlmrshl@gmail.com
License: MIT
Platform: UNKNOWN
Classifier: Programming Language :: Python
Classifier: Programming Language :: Python :: 2.7
Classifier: Programming Language :: Python :: 3
Classifier: Programming Language :: C
Classifier: Development Status :: 3 - Alpha
Classifier: Intended Audience :: Developers
Classifier: License :: OSI Approved :: MIT License
Classifier: Topic :: Multimedia :: Graphics
Classifier: Topic :: Software Development :: Libraries :: Python Modules
